bv/utils.pxd
bv/descriptor.py
bv/dictionary.cpython-311-darwin.so
bv/frame.pxd
bv/logging.py
bv/descriptor.pxd
bv/descriptor.cpython-311-darwin.so
bv/packet.pyi
bv/buffer.pyi
bv/error.pyi
bv/logging.pxd
bv/plane.cpython-311-darwin.so
bv/error.py
bv/format.pxd
bv/_core.pyi
bv/bitstream.pxd
bv/bitstream.pyi
bv/format.pyi
bv/__init__.pxd
bv/stream.cpython-311-darwin.so
bv/bitstream.py
bv/logging.cpython-311-darwin.so
bv/logging.pyi
bv/error.pxd
bv/datasets.py
bv/buffer.pxd
bv/packet.pxd
bv/__init__.py
bv/format.py
bv/descriptor.pyi
bv/about.py
bv/frame.pyi
bv/stream.py
bv/_core.py
bv/plane.pyi
bv/dictionary.pyi
bv/frame.cpython-311-darwin.so
bv/utils.cpython-311-darwin.so
bv/utils.py
bv/frame.py
bv/buffer.py
bv/bitstream.cpython-311-darwin.so
bv/py.typed
bv/stream.pxd
bv/packet.py
bv/_core.cpython-311-darwin.so
bv/stream.pyi
bv/error.cpython-311-darwin.so
bv/dictionary.py
bv/format.cpython-311-darwin.so
bv/packet.cpython-311-darwin.so
bv/dictionary.pxd
bv/plane.py
bv/__main__.py
bv/plane.pxd
bv/buffer.cpython-311-darwin.so
bv/video/frame.pxd
bv/video/codeccontext.cpython-311-darwin.so
bv/video/reformatter.cpython-311-darwin.so
bv/video/plane.cpython-311-darwin.so
bv/video/reformatter.pxd
bv/video/format.pxd
bv/video/__init__.pyi
bv/video/reformatter.pyi
bv/video/format.pyi
bv/video/__init__.pxd
bv/video/stream.cpython-311-darwin.so
bv/video/__init__.py
bv/video/reformatter.py
bv/video/format.py
bv/video/frame.pyi
bv/video/stream.py
bv/video/plane.pyi
bv/video/codeccontext.py
bv/video/frame.cpython-311-darwin.so
bv/video/codeccontext.pxd
bv/video/frame.py
bv/video/stream.pxd
bv/video/stream.pyi
bv/video/format.cpython-311-darwin.so
bv/video/codeccontext.pyi
bv/video/plane.py
bv/video/plane.pxd
bv/codec/codec.cpython-311-darwin.so
bv/codec/hwaccel.pyi
bv/codec/hwaccel.cpython-311-darwin.so
bv/codec/context.pyi
bv/codec/__init__.pxd
bv/codec/context.pxd
bv/codec/__init__.py
basswood_av-15.2.1.dist-info/RECORD
basswood_av-15.2.1.dist-info/WHEEL
basswood_av-15.2.1.dist-info/entry_points.txt
basswood_av-15.2.1.dist-info/top_level.txt
basswood_av-15.2.1.dist-info/METADATA
basswood_av-15.2.1.dist-info/licenses/AUTHORS.rst
basswood_av-15.2.1.dist-info/licenses/AUTHORS.py
basswood_av-15.2.1.dist-info/licenses/LICENSE.txt
